vector_bridge/__init__.py
vector_bridge/async_io/__init__.py
vector_bridge/async_io/admin/__init__.py
vector_bridge/async_io/admin/api_keys.py
vector_bridge/async_io/admin/functions.py
vector_bridge/async_io/admin/instructions.py
vector_bridge/async_io/admin/integrations.py
vector_bridge/async_io/admin/mcp.py
vector_bridge/async_io/admin/organization.py
vector_bridge/async_io/admin/security_groups.py
vector_bridge/async_io/admin/settings.py
vector_bridge/async_io/admin/vector_db/__init__.py
vector_bridge/async_io/admin/vector_db/changeset.py
vector_bridge/async_io/admin/vector_db/state.py
vector_bridge/async_io/client/__init__.py
vector_bridge/async_io/client/ai_knowledge/__init__.py
vector_bridge/async_io/client/ai_knowledge/file_storage.py
vector_bridge/async_io/client/chat.py
vector_bridge/async_io/client/function.py
vector_bridge/async_io/client/logs.py
vector_bridge/async_io/client/mcp.py
vector_bridge/async_io/client/notifications.py
vector_bridge/async_io/client/query.py
vector_bridge/async_io/client/tasks.py
vector_bridge/async_io/client/usage.py
vector_bridge/async_io/client/user.py
vector_bridge/async_io/client/workflows.py
vector_bridge/schema/__init__.py
vector_bridge/schema/ai_knowledge/__init__.py
vector_bridge/schema/ai_knowledge/filesystem.py
vector_bridge/schema/api_keys.py
vector_bridge/schema/chat.py
vector_bridge/schema/error.py
vector_bridge/schema/errors/__init__.py
vector_bridge/schema/errors/ai_knowledge.py
vector_bridge/schema/errors/api_keys.py
vector_bridge/schema/errors/base.py
vector_bridge/schema/errors/chat.py
vector_bridge/schema/errors/functions.py
vector_bridge/schema/errors/instructions.py
vector_bridge/schema/errors/integrations.py
vector_bridge/schema/errors/logs.py
vector_bridge/schema/errors/mcp.py
vector_bridge/schema/errors/message.py
vector_bridge/schema/errors/notifications.py
vector_bridge/schema/errors/organization.py
vector_bridge/schema/errors/queries.py
vector_bridge/schema/errors/security_groups.py
vector_bridge-2.2.0.dist-info/METADATA
vector_bridge-2.2.0.dist-info/WHEEL
vector_bridge-2.2.0.dist-info/RECORD
