Metadata-Version: 2.1
Name: vector-bridge
Version: 2.2.0
Summary: A client library for accessing VectorBridge.ai: API
Requires-Python: >=3.10,<4.0
Classifier: Programming Language :: Python :: 3
Classifier: Programming Language :: Python :: 3.10
Classifier: Programming Language :: Python :: 3.11
Classifier: Programming Language :: Python :: 3.12
Requires-Dist: aiofiles (>=24.1.0,<25.0.0)
Requires-Dist: aiohttp (>=3.12.14,<4.0.0)
Requires-Dist: pydantic (>=2.10.6,<3.0.0)
Requires-Dist: python-dateutil (==2.9.0.post0)
Requires-Dist: redis (>=6.2.0,<7.0.0)
Requires-Dist: requests (>=2.32.3,<3.0.0)
Requires-Dist: stdlib-list (==0.11.1)
Requires-Dist: weaviate-client (>=4.10.4,<5.0.0)
